torch_lp-0.1.1.dist-info/DESCRIPTION.rst
torch_lp-0.1.1.dist-info/METADATA
torch_lp-0.1.1.dist-info/RECORD
torch_lp-0.1.1.dist-info/WHEEL
torch_lp-0.1.1.dist-info/metadata.json
torch_lp-0.1.1.dist-info/top_level.txt
torchlp/__init__.py
