Metadata-Version: 2.0
Name: torch-lp
Version: 0.1.1
Summary: quantization simulation tools for Pytorch
Home-page: UNKNOWN
Author: Bingzhe
Author-email: wubingzheagent@gmail.com
License: MIT
Platform: UNKNOWN
